virtual_consultant_cli/__init__.py
virtual_consultant_cli/cli.py
virtual_consultant_cli/py.typed
virtual_consultant_cli/scripts/build.py
virtual_consultant_cli/templates/.cursor/tasks/eliza_tasks.json
virtual_consultant_cli/templates/.editorconfig
virtual_consultant_cli/templates/.env.example
virtual_consultant_cli/templates/.eslintrc.json
virtual_consultant_cli/templates/.github/workflows/eliza.yml
virtual_consultant_cli/templates/.gitignore
virtual_consultant_cli/templates/.gitpod.yml
virtual_consultant_cli/templates/.npmrc
virtual_consultant_cli/templates/.nvmrc
virtual_consultant_cli/templates/.prettierignore
virtual_consultant_cli/templates/Dockerfile
virtual_consultant_cli/templates/Dockerfile.docs
virtual_consultant_cli/templates/docker-compose.yml
virtual_consultant_cli/templates/eliza/eliza.py
virtual_consultant_cli/templates/main.wasp
virtual_consultant_cli/templates/src/operations/actions.ts
virtual_consultant_cli/templates/src/operations/queries.ts
virtual_consultant_cli/templates/src/pages/Main.tsx
virtual_consultant_cli/utils/__init__.py
virtual_consultant_cli/utils/dependencies.py
virtual_consultant_cli/utils/docs.py
virtual_consultant_cli/utils/project.py
virtual_consultant_cli/utils/py.typed
virtual_consultant_cli-0.2.0.dist-info/LICENSE
virtual_consultant_cli-0.2.0.dist-info/METADATA
virtual_consultant_cli-0.2.0.dist-info/WHEEL
virtual_consultant_cli-0.2.0.dist-info/entry_points.txt
virtual_consultant_cli-0.2.0.dist-info/RECORD
