Metadata-Version: 2.1
Name: virtual-consultant-cli
Version: 0.2.0
Summary: A professional CLI tool for creating and managing Virtual Consultant projects
License: MIT
Keywords: cli,automation,project-management,virtual-consultant
Author: Your Name
Author-email: your.email@example.com
Requires-Python: >=3.9,<4.0
Classifier: Development Status :: 4 - Beta
Classifier: Environment :: Console
Classifier: Intended Audience :: Developers
Classifier: License :: OSI Approved :: MIT License
Classifier: Programming Language :: Python :: 3
Classifier: Programming Language :: Python :: 3.9
Classifier: Programming Language :: Python :: 3.10
Classifier: Programming Language :: Python :: 3.11
Classifier: Programming Language :: Python :: 3.12
Classifier: Programming Language :: Python :: 3.13
Classifier: Topic :: Software Development :: Libraries :: Python Modules
Requires-Dist: click (>=8.1.8,<9.0.0)
Requires-Dist: rich (>=13.0.0,<14.0.0)
